CHANGES.txt
LICENSE.txt
MANIFEST.in
README.md
TESTING.txt
pyproject.toml
setup.cfg
setup.py
tox.ini
src/pyramid_sqlassist/__init__.py
src/pyramid_sqlassist/interface.py
src/pyramid_sqlassist/objects.py
src/pyramid_sqlassist/py.typed
src/pyramid_sqlassist.egg-info/PKG-INFO
src/pyramid_sqlassist.egg-info/SOURCES.txt
src/pyramid_sqlassist.egg-info/dependency_links.txt
src/pyramid_sqlassist.egg-info/not-zip-safe
src/pyramid_sqlassist.egg-info/requires.txt
src/pyramid_sqlassist.egg-info/top_level.txt
src/pyramid_sqlassist/debugtoolbar/__init__.py
src/pyramid_sqlassist/debugtoolbar/panels/__init__.py
src/pyramid_sqlassist/debugtoolbar/panels/sqlassist.py
src/pyramid_sqlassist/debugtoolbar/panels/templates/sqlassist.dbtmako
tests/__init__.py
tests/_utils.py
tests/test_app.py
tests/test_unit.py
tests/pyramid_testapp/__init__.py
tests/pyramid_testapp/views.py
tests/pyramid_testapp/model/__init__.py
tests/pyramid_testapp/model/model_objects.py
tests/pyramid_testapp/templates/splash.mako
tests/pyramid_testapp/templates/test_results.mako