Metadata-Version: 2.4
Name: pyramid_sqlassist
Version: 0.16.0
Summary: Efficiently manage multiple SqlAlchemy connections for Pyramid
Home-page: https://github.com/jvanasco/pyramid_sqlassist
Author: Jonathan Vanasco
Author-email: jonathan@findmeon.com
License: MIT
Keywords: web Pyramid SQLAlchemy
Classifier: Intended Audience :: Developers
Classifier: Framework :: Pyramid
Classifier: Programming Language :: Python :: 3
Classifier: Programming Language :: Python :: 3.7
Classifier: Programming Language :: Python :: 3.8
Classifier: Programming Language :: Python :: 3.9
Classifier: Programming Language :: Python :: 3.10
Classifier: Programming Language :: Python :: 3.11
Classifier: Programming Language :: Python :: 3.12
Classifier: Programming Language :: Python :: 3.13
License-File: LICENSE.txt
Requires-Dist: SQLAlchemy>=2.0
Requires-Dist: pyramid
Requires-Dist: typing_extensions
Provides-Extra: testing
Requires-Dist: mypy; extra == "testing"
Requires-Dist: pytest; extra == "testing"
Requires-Dist: pyramid_mako; extra == "testing"
Requires-Dist: pyramid_debugtoolbar; extra == "testing"
Requires-Dist: pyramid_tm; extra == "testing"
Requires-Dist: transaction; extra == "testing"
Requires-Dist: webtest; extra == "testing"
Requires-Dist: zope.sqlalchemy>=1.6; extra == "testing"
Dynamic: author
Dynamic: author-email
Dynamic: classifier
Dynamic: description
Dynamic: description-content-type
Dynamic: home-page
Dynamic: keywords
Dynamic: license
Dynamic: license-file
Dynamic: provides-extra
Dynamic: requires-dist
Dynamic: summary
